AndroStats/__init__.py
AndroStats/data/param_percentiles.csv
AndroStats/performance.py
AndroStats/plotting.py
androstats-0.1.13.dist-info/LICENSE
androstats-0.1.13.dist-info/METADATA
androstats-0.1.13.dist-info/WHEEL
androstats-0.1.13.dist-info/RECORD
