Metadata-Version: 2.1
Name: AndroStats
Version: 0.1.13
Summary: Stats for andrology
Author: M-Jeffryes
Author-email: michael@maleboxhealth.com
Requires-Python: >=3.10,<4.0
Classifier: Programming Language :: Python :: 3
Classifier: Programming Language :: Python :: 3.10
Classifier: Programming Language :: Python :: 3.11
Classifier: Programming Language :: Python :: 3.12
Requires-Dist: matplotlib (==3.8.3)
Requires-Dist: numpy (>=1.26.4,<2.0.0)
Requires-Dist: seaborn (>=0.13.2,<0.14.0)
